gemben/__init__.py
gemben/_version.py
gemben/c_exe/__init__.py
gemben/c_ext/__init__.py
gemben/c_src/__init__.py
gemben/embedding/__init__.py
gemben/embedding/aa.py
gemben/embedding/ae_static.py
gemben/embedding/cn.py
gemben/embedding/gcn.py
gemben/embedding/gf.py
gemben/embedding/hope.py
gemben/embedding/jc.py
gemben/embedding/lap.py
gemben/embedding/lle.py
gemben/embedding/node2vec.py
gemben/embedding/pa.py
gemben/embedding/rand.py
gemben/embedding/sdne.py
gemben/embedding/sdne_utils.py
gemben/embedding/static_graph_embedding.py
gemben/embedding/vae.py
gemben/evaluation/__init__.py
gemben/evaluation/evaluate_graph_reconstruction.py
gemben/evaluation/evaluate_link_prediction.py
gemben/evaluation/evaluate_node_classification.py
gemben/evaluation/metrics.py
gemben/evaluation/visualize_embedding.py
gemben/experiments/__init__.py
gemben/experiments/exp.py
gemben/experiments/exp_bay.py
gemben/experiments/exp_benchmark.py
gemben/experiments/exp_benchmark2.py
gemben/experiments/experiment.py
gemben/experiments/plot_result.py
gemben/plots/__init__.py
gemben/utils/__init__.py
gemben/utils/bayesian_opt.py
gemben/utils/embed_util.py
gemben/utils/evaluation_util.py
gemben/utils/graph_gens.py
gemben/utils/graph_util.py
gemben/utils/kronecker_generator.py
gemben/utils/kronecker_init_matrix.py
gemben/utils/lrf_gen.py
gemben/utils/plot_util.py
gemben-0.0.4.dist-info/LICENSE
gemben-0.0.4.dist-info/METADATA
gemben-0.0.4.dist-info/WHEEL
gemben-0.0.4.dist-info/top_level.txt
gemben-0.0.4.dist-info/RECORD
