Metadata-Version: 2.1
Name: gemben
Version: 0.0.4
Summary: Benchmark for Graph Embedding Algorithms
Home-page: https://github.com/Sujit-O/gemben.git
Author: Palash Goyal, Di Huang, Ankita Goswami, Sujit Rokka Chhetri, Arquimedes Canedo and Emilio Ferrara
Author-email: palashgo@usc.edu
License: UNKNOWN
Platform: UNKNOWN
Classifier: Programming Language :: Python :: 3.6
Classifier: License :: OSI Approved :: MIT License
Classifier: Operating System :: OS Independent
Requires-Dist: cmake (>=3.14.4)
Requires-Dist: matplotlib
Requires-Dist: pandas (>=0.24.2)
Requires-Dist: seaborn (>=0.9.0)
Requires-Dist: tables (>=3.5.2)
Requires-Dist: networkx (>=2.3)
Requires-Dist: Keras (>=2.2.4)
Requires-Dist: Theano (>=1.0.4)
Requires-Dist: numpy (>=1.16.4)
Requires-Dist: scipy (>=1.3.0)
Requires-Dist: sklearn (>=0.0)
Requires-Dist: bayesian-optimization (>=1.0.1)
Requires-Dist: tensorflow (==1.14.0)
Requires-Dist: pyvis
Provides-Extra: networkit
Requires-Dist: cmake (>=3.12.0) ; extra == 'networkit'
